setup.py
QAplatform/__init__.py
QAplatform/src/QAsearch.py
QAplatform/src/__init__.py
QAplatform/src/analysis/__init__.py
QAplatform/src/analysis/analysis_base.py
QAplatform/src/analysis/analysis_strategy.py
QAplatform/src/analysis/dataclean.py
QAplatform/src/analysis/senemb.py
QAplatform/src/analysis/wordseg.py
QAplatform/src/common/__init__.py
QAplatform/src/common/logger.py
QAplatform/src/common/utils.py
QAplatform/src/matching/__init__.py
QAplatform/src/matching/matching_base.py
QAplatform/src/matching/matching_strategy.py
QAplatform/src/matching/lexical/__init__.py
QAplatform/src/matching/lexical/bm25_matcher.py
QAplatform/src/matching/lexical/jaccard_matcher.py
QAplatform/src/matching/lexical/tfidf_matcher.py
QAplatform/src/matching/semantic/__init__.py
QAplatform/src/matching/semantic/bert_matcher.py
QAplatform/src/matching/semantic/embedding_matcher.py
QAplatform/src/matching/semantic/knrm.py
QAplatform/src/matching/semantic/bert/__init__.py
QAplatform/src/matching/semantic/bert/run_classifier.py
QAplatform/src/matching/semantic/bert/similarity.py
QAplatform/src/matching/semantic/bert/tokenization.py
QAplatform/src/rank/__init__.py
QAplatform/src/rank/rank_base.py
QAplatform/src/rank/rank_strategy.py
QAplatform/src/rank/predictor/__init__.py
QAplatform/src/rank/predictor/bert_model.py
QAplatform/src/rank/predictor/linear_model.py
QAplatform/src/retrieval/__init__.py
QAplatform/src/retrieval/retrieval_base.py
QAplatform/src/retrieval/retrieval_strategy.py
QAplatform/src/retrieval/manual/__init__.py
QAplatform/src/retrieval/manual/manual_index.py
QAplatform/src/retrieval/semantic/__init__.py
QAplatform/src/retrieval/semantic/annoy_index.py
QAplatform/src/retrieval/semantic/faiss_index.py
QAplatform/src/retrieval/term/__init__.py
qatools_ifchange.egg-info/PKG-INFO
qatools_ifchange.egg-info/SOURCES.txt
qatools_ifchange.egg-info/dependency_links.txt
qatools_ifchange.egg-info/not-zip-safe
qatools_ifchange.egg-info/requires.txt
qatools_ifchange.egg-info/top_level.txt