Metadata-Version: 2.1
Name: qatools-ifchange
Version: 0.0.8
Summary: fix encoding version
Home-page: https://github.com
Author: LH19880520
Author-email: peng.wang@ifchange.com
License: ifchange
Platform: UNKNOWN
